odoo/addons/rma_repair/README.rst
odoo/addons/rma_repair/__init__.py
odoo/addons/rma_repair/__manifest__.py
odoo/addons/rma_repair/data/rma_operation_data.xml
odoo/addons/rma_repair/i18n/ca.po
odoo/addons/rma_repair/i18n/es.po
odoo/addons/rma_repair/i18n/it.po
odoo/addons/rma_repair/i18n/rma_repair.pot
odoo/addons/rma_repair/models/__init__.py
odoo/addons/rma_repair/models/repair.py
odoo/addons/rma_repair/models/rma.py
odoo/addons/rma_repair/models/rma_operation.py
odoo/addons/rma_repair/readme/CONTRIBUTORS.md
odoo/addons/rma_repair/readme/DESCRIPTION.md
odoo/addons/rma_repair/readme/USAGE.md
odoo/addons/rma_repair/static/description/icon.png
odoo/addons/rma_repair/static/description/icon.svg
odoo/addons/rma_repair/static/description/index.html
odoo/addons/rma_repair/tests/__init__.py
odoo/addons/rma_repair/tests/test_rma_repair_order.py
odoo/addons/rma_repair/views/repair_views.xml
odoo/addons/rma_repair/views/rma_operation.xml
odoo/addons/rma_repair/views/rma_views.xml
odoo_addon_rma_repair-17.0.1.0.2.dist-info/METADATA
odoo_addon_rma_repair-17.0.1.0.2.dist-info/WHEEL
odoo_addon_rma_repair-17.0.1.0.2.dist-info/top_level.txt
odoo_addon_rma_repair-17.0.1.0.2.dist-info/RECORD
