Metadata-Version: 2.1
Name: odoo-addon-rma_repair
Version: 17.0.1.0.2
Requires-Python: >=3.10
Requires-Dist: odoo-addon-rma_lot>=17.0dev,<17.1dev
Requires-Dist: odoo>=17.0a,<17.1dev
Summary: Create a repair order from rma
Home-page: https://github.com/OCA/rma
License: AGPL-3
Author: Antoni Marroig, Odoo Community Association (OCA)
Author-email: support@odoo-community.org
Classifier: Programming Language :: Python
Classifier: Framework :: Odoo
Classifier: Framework :: Odoo :: 17.0
Classifier: License :: OSI Approved :: GNU Affero General Public License v3
